mygeo_dev/__init__.py
mygeo_dev/common.py
mygeo_dev/mygeo_dev.py
mygeo_dev-0.0.1.dist-info/licenses/LICENSE
mygeo_dev-0.0.1.dist-info/METADATA
mygeo_dev-0.0.1.dist-info/WHEEL
mygeo_dev-0.0.1.dist-info/entry_points.txt
mygeo_dev-0.0.1.dist-info/top_level.txt
mygeo_dev-0.0.1.dist-info/RECORD
